trytond/modules/party_admin_edit/README.rst
trytond/modules/party_admin_edit/__init__.py
trytond/modules/party_admin_edit/party.py
trytond/modules/party_admin_edit/party.xml
trytond/modules/party_admin_edit/tryton.cfg
trytond/modules/party_admin_edit/locale/de.po
trytond/modules/party_admin_edit/locale/en.po
trytond/modules/party_admin_edit/tests/__init__.py
trytond/modules/party_admin_edit/tests/test_party.py
mds_party_admin_edit-5.0.0.dist-info/METADATA
mds_party_admin_edit-5.0.0.dist-info/WHEEL
mds_party_admin_edit-5.0.0.dist-info/entry_points.txt
mds_party_admin_edit-5.0.0.dist-info/top_level.txt
mds_party_admin_edit-5.0.0.dist-info/RECORD
